Metadata-Version: 2.3
Name: substrafl
Version: 1.0.0
Summary: A high-level federated learning Python library to run     federated learning experiments at scale on a Substra network
Project-URL: Documentation, https://docs.substra.org/en/stable/
Project-URL: Repository, https://github.com/Substra/substrafl
Project-URL: Changelog, https://github.com/Substra/substrafl/blob/main/CHANGELOG.md
Author: Owkin, Inc.
License: 
License-File: LICENSE
Keywords: substrafl
Classifier: Operating System :: OS Independent
Classifier: Programming Language :: Python :: 3.10
Classifier: Programming Language :: Python :: 3.11
Classifier: Programming Language :: Python :: 3.12
Requires-Python: >=3.10
Requires-Dist: cloudpickle>=1.6.0
Requires-Dist: numpy>=1.24
Requires-Dist: packaging
Requires-Dist: pip-tools
Requires-Dist: pip>=21.2
Requires-Dist: pydantic<3.0,>=2.3.0
Requires-Dist: six
Requires-Dist: substratools~=1.0.0
Requires-Dist: substra~=1.0.0
Requires-Dist: tqdm
Requires-Dist: wheel
Provides-Extra: dev
Requires-Dist: docker; extra == 'dev'
Requires-Dist: nbmake>=1.4.3; extra == 'dev'
Requires-Dist: pre-commit>=2.13.0; extra == 'dev'
Requires-Dist: pytest-cov>=2.12.0; extra == 'dev'
Requires-Dist: pytest-mock; extra == 'dev'
Requires-Dist: pytest>=6.2.4; extra == 'dev'
Requires-Dist: torch!=1.12.0,>=1.9.1; extra == 'dev'
Requires-Dist: towncrier; extra == 'dev'
Requires-Dist: types-pyyaml>=6.0.0; extra == 'dev'
